README
setup.py
./hsalf/__init__.py
./hsalf/swf.py
./hsalf/test_swf.py
hsalf/__init__.py
hsalf/swf.py
hsalf/test_swf.py
hsalf.egg-info/PKG-INFO
hsalf.egg-info/SOURCES.txt
hsalf.egg-info/dependency_links.txt
hsalf.egg-info/top_level.txt