Metadata-Version: 1.0
Name: hsalf
Version: 0.0.1
Summary: Hsalf is a pure Python library to read and write Flash files (SWF).
Home-page: https://bitbucket.org/namn/hsalf/overview
Author: Nam T. Nguyen
Author-email: namn@bluemoon.com.vn
License: MIT
Platform: Any
Classifier: Development Status :: 3 - Alpha
Classifier: Intended Audience :: Developers
Classifier: License :: OSI Approved :: MIT License
Classifier: Operating System :: OS Independent
Classifier: Programming Language :: Python
Classifier: Topic :: Internet :: WWW/HTTP
Classifier: Topic :: Multimedia
Classifier: Topic :: Security
Classifier: Topic :: Software Development :: Assemblers
Classifier: Topic :: Software Development :: Disassemblers
Classifier: Topic :: Software Development :: Libraries :: Python Modules
